asteroid/__init__.py
asteroid/frontend.py
asteroid/globals.py
asteroid/interp.py
asteroid/lex.py
asteroid/mad.py
asteroid/repl.py
asteroid/state.py
asteroid/support.py
asteroid/symtab.py
asteroid/version.py
asteroid/walk.py
asteroid/modules/bitwise.ast
asteroid/modules/dataframe.ast
asteroid/modules/hash.ast
asteroid/modules/io.ast
asteroid/modules/math.ast
asteroid/modules/os.ast
asteroid/modules/patterns.ast
asteroid/modules/pick.ast
asteroid/modules/prologue.ast
asteroid/modules/random.ast
asteroid/modules/set.ast
asteroid/modules/sort.ast
asteroid/modules/stream.ast
asteroid/modules/util.ast
asteroid/modules/vector.ast
asteroid_lang-2.0.2.dist-info/LICENSE
asteroid_lang-2.0.2.dist-info/METADATA
asteroid_lang-2.0.2.dist-info/WHEEL
asteroid_lang-2.0.2.dist-info/entry_points.txt
asteroid_lang-2.0.2.dist-info/top_level.txt
asteroid_lang-2.0.2.dist-info/RECORD
