Metadata-Version: 2.1
Name: asteroid-lang
Version: 2.0.2
Summary: A modern, multi-paradigm programming language.
Home-page: https://asteroid-lang.org
Author: University of Rhode Island
Author-email: lutzhamel@uri.edu
Project-URL: Documentation, https://asteroid-lang.readthedocs.io
Project-URL: Bug Tracker, https://github.com/asteroid-lang/asteroid/issues
Classifier: Programming Language :: Python :: 3
Classifier: License :: OSI Approved :: MIT License
Classifier: Operating System :: OS Independent
Requires-Python: >=3.10
License-File: LICENSE
Requires-Dist: pandas
Requires-Dist: numpy
Requires-Dist: matplotlib
Requires-Dist: pyreadline3
